ibm_datastage_api/__init__.py
ibm_datastage_api/ibm_datastage_api.py
ibm_datastage_api/ibm_datastage_api_errors.py
ibm_datastage_api/ibm_datastage_api_structures.py
ibm_datastage_api/ibm_datastage_api_utils.py
IBM_DataStage_API-1.1.0.dist-info/LICENSE
IBM_DataStage_API-1.1.0.dist-info/METADATA
IBM_DataStage_API-1.1.0.dist-info/WHEEL
IBM_DataStage_API-1.1.0.dist-info/top_level.txt
IBM_DataStage_API-1.1.0.dist-info/RECORD
