Metadata-Version: 2.1
Name: IBM-DataStage-API
Version: 1.1.0
Summary: IBM DataStage API on python
Home-page: https://github.com/reijnnn/IBM-DataStage-API
Author: reijnnn
Author-email: reijnnn@gmail.com
License: MIT
Keywords: IBM DS API InfoSphere DataStage python3 ctypes
Platform: UNKNOWN
Classifier: Programming Language :: Python :: 3
